watchgate_gateway/__init__.py
watchgate_gateway-0.1.0.dist-info/METADATA
watchgate_gateway-0.1.0.dist-info/WHEEL
watchgate_gateway-0.1.0.dist-info/RECORD
