Metadata-Version: 2.4
Name: watchgate-gateway
Version: 0.1.0
Summary: Secure MCP gateway with auditing and access control (core gateway without TUI)
License: Apache-2.0
Requires-Python: >=3.11
